README.md
setup.py
kube_bench_report_converter/__init__.py
kube_bench_report_converter/command_line.py
kube_bench_report_converter/parser.py
kube_bench_report_converter/writer.py
kube_bench_report_converter.egg-info/PKG-INFO
kube_bench_report_converter.egg-info/SOURCES.txt
kube_bench_report_converter.egg-info/dependency_links.txt
kube_bench_report_converter.egg-info/entry_points.txt
kube_bench_report_converter.egg-info/not-zip-safe
kube_bench_report_converter.egg-info/top_level.txt