Metadata-Version: 2.1
Name: kube-bench-report-converter
Version: 0.0.1
Summary: Converts kube-bench checks console output to CSV.
Home-page: https://github.com/build-failure/kube-bench-report-converter
Author: Michael Lewkowski
Author-email: michael@lewkowski.de
Maintainer: Michael Lewkowski
Maintainer-email: michael@lewkowski.de
License: MIT
Project-URL: Code, https://github.com/build-failure/kube-bench-report-converter
Project-URL: Issue tracker, https://github.com/build-failure/kube-bench-report-converter/issues
Keywords: kube-bench report convert csv
Platform: UNKNOWN
Classifier: Programming Language :: Python :: 2
Classifier: Programming Language :: Python :: 2.7
Classifier: Programming Language :: Python :: 3
Classifier: Programming Language :: Python :: 3.6
Classifier: Programming Language :: Python :: 3.7
Classifier: Programming Language :: Python :: 3.8
Classifier: License :: OSI Approved :: MIT License
Classifier: Operating System :: OS Independent
Requires-Python: >=2.7,!=3.0.*,!=3.1.*,!=3.2.*,!=3.3.*,!=3.4.*,!=3.5.*
